.gitignore
LICENSE.md
MANIFEST.in
README.md
environment.yml
pytest.ini
requirements.txt
setup.cfg
setup.py
update_docs.sh
docs/Makefile
docs/make.bat
docs/source/conf.py
docs/source/index.rst
pandas_htools/__init__.py
pandas_htools/main.py
pandas_htools.egg-info/PKG-INFO
pandas_htools.egg-info/SOURCES.txt
pandas_htools.egg-info/dependency_links.txt
pandas_htools.egg-info/requires.txt
pandas_htools.egg-info/top_level.txt
tests/__init__.py
tests/conftest.py
tests/test_ends.py
tests/test_filter_by_count.py
tests/test_grouped_mode.py
tests/test_impute.py
tests/test_lambda_sort.py
tests/test_pprint.py
tests/test_target_encoding.py
tests/test_top_categories.py
tests/test_vcounts.py