Metadata-Version: 1.1
Name: pandas-htools
Version: 0.0.3
Summary: Tools for Exploratory data analysis with Pandas
Home-page: https://github.com/hdmamin/pandas_htools
Author: Harrison Mamin
Author-email: UNKNOWN
License: BSD
Download-URL: https://github.com/hdmamin/pandas_htools/tarball/0.0.3
Platform: UNKNOWN
Classifier: Development Status :: 3 - Alpha
Classifier: Intended Audience :: Developers
Classifier: Programming Language :: Python :: 3
